torchcompat/core/__init__.py
torchcompat/core/errors.py
torchcompat/core/load.py
torchcompat/plugins/__init__.py
torchcompat/plugins/cpu/__init__.py
torchcompat/plugins/cuda/__init__.py
torchcompat/plugins/gaudi/__init__.py
torchcompat/plugins/rocm/__init__.py
torchcompat/plugins/xpu/__init__.py
torchcompat-1.1.4.dist-info/LICENSE
torchcompat-1.1.4.dist-info/METADATA
torchcompat-1.1.4.dist-info/WHEEL
torchcompat-1.1.4.dist-info/top_level.txt
torchcompat-1.1.4.dist-info/RECORD
