Metadata-Version: 2.1
Name: torchcompat
Version: 1.1.4
Summary: torch compatibility layer
Home-page: https://torchcompat.readthedocs.io
Author: Anonymous
Author-email: anony@mous.com
License: BSD 3-Clause License
Classifier: License :: OSI Approved :: BSD License
Classifier: Programming Language :: Python :: 3.8
Classifier: Programming Language :: Python :: 3.9
Classifier: Programming Language :: Python :: 3.10
Classifier: Operating System :: OS Independent
License-File: LICENSE
Requires-Dist: importlib-resources
Provides-Extra: all
Requires-Dist: importlib-resources ; extra == 'all'
Requires-Dist: torch ; extra == 'all'
Provides-Extra: base
Requires-Dist: torch ; extra == 'base'
Provides-Extra: plugins
Requires-Dist: importlib-resources ; extra == 'plugins'
